escher/__init__.py
escher/plots.py
escher/urls.py
escher/util.py
escher/validate.py
escher/version.py
escher/static/escher.min.js
escher/static/escher.min.js.map
escher/static/extension.js
escher/static/package.json
escher/templates/standalone.html
mcescher-1.7.0b17.data/data/etc/jupyter/nbconfig/notebook.d/escher.json
mcescher-1.7.0b17.data/data/share/jupyter/nbextensions/escher/escher.min.js
mcescher-1.7.0b17.data/data/share/jupyter/nbextensions/escher/escher.min.js.map
mcescher-1.7.0b17.data/data/share/jupyter/nbextensions/escher/extension.js
mcescher-1.7.0b17.dist-info/METADATA
mcescher-1.7.0b17.dist-info/WHEEL
mcescher-1.7.0b17.dist-info/top_level.txt
mcescher-1.7.0b17.dist-info/RECORD
