Metadata-Version: 2.1
Name: mcescher
Version: 1.7.0b17
Summary: Escher: A Web Application for Building, Sharing, and Embedding Data-Rich Visualizations of Metabolic Pathways
Home-page: https://escher.github.io
Author: Zachary King
License: MIT
Keywords: visualization,pathway map,metabolism,genome-scale-model,web application,D3.js,biojs
Classifier: Development Status :: 5 - Production/Stable
Classifier: License :: OSI Approved :: MIT License
Classifier: Topic :: Scientific/Engineering
Classifier: Topic :: Scientific/Engineering :: Visualization
Classifier: Programming Language :: Python :: 3
Classifier: Programming Language :: Python :: 3.6
Classifier: Programming Language :: Python :: 3.7
Classifier: Operating System :: OS Independent
Requires-Dist: Jinja2 (<4,>=3.1.2)
Requires-Dist: cobra (>=0.5.0)
Requires-Dist: jsonschema (<3,>=2.4.0)
Requires-Dist: ipywidgets (<8,>=7.1.0)
Requires-Dist: pandas (>=0.18)
Provides-Extra: dev
Requires-Dist: pytest (<5,>=4.0.1) ; extra == 'dev'
Provides-Extra: docs
Requires-Dist: sphinx (>=1.2) ; extra == 'docs'
Requires-Dist: sphinx-rtd-theme (>=0.1.6) ; extra == 'docs'
